pybluesky/__init__.py
pybluesky/actor.py
pybluesky/cursor.py
pybluesky/feed.py
pybluesky/graph.py
pybluesky/notification.py
pybluesky/repo.py
pybluesky/server.py
PyBluesky-0.0.2.dist-info/LICENSE
PyBluesky-0.0.2.dist-info/METADATA
PyBluesky-0.0.2.dist-info/WHEEL
PyBluesky-0.0.2.dist-info/top_level.txt
PyBluesky-0.0.2.dist-info/RECORD
