Metadata-Version: 2.1
Name: PyBluesky
Version: 0.0.2
Summary: Bluesky.Social AT Protocol API Library
Home-page: https://github.com/mitian233/pybluesky
Author: Mitian233
Author-email: kasumi@bangdream.moe
Classifier: Development Status :: 1 - Planning
Classifier: Intended Audience :: Developers
Classifier: License :: OSI Approved :: MIT License
Classifier: Operating System :: OS Independent
Classifier: Programming Language :: Python
Classifier: Programming Language :: Python :: 3
Classifier: Programming Language :: Python :: 3.6
Classifier: Programming Language :: Python :: 3.7
Classifier: Programming Language :: Python :: 3.8
Classifier: Programming Language :: Python :: 3.9
Classifier: Programming Language :: Python :: 3.10
License-File: LICENSE
Requires-Dist: requests
